{
  "rule_id": "maintenance.civil-check.measured_value.6.26.2",
  "version": "2026-04",
  "uri": "v://normref.com/rule/maintenance/civil-check/measured_value@2026-04",
  "category": "maintenance/civil-check",
  "field_key": "measured_value",
  "operator": "lte",
  "threshold_value": "1",
  "unit": "mm",
  "severity": "mandatory",
  "norm_ref": "6.26.2",
  "source_line": "1 桩位(mm) ≤50 全站仪：每桩检查",
  "confidence": 0.82,
  "ingest_job_id": "ingest-03b88bfc79ba4c68",
  "candidate_id": "cand-8525e09c8a28",
  "source_std_code": "JTG-5220-2020",
  "source_level": "industry",
  "scope": "industry",
  "hash": "sha256:9b595a9775fd7af3f7c91485e719a4ff9c987eec61d8ea63e9ea89b7458b88a8"
}