{
  "rule_id": "maintenance.civil-check.measured_value.5.5.1",
  "version": "2026-04",
  "uri": "v://normref.com/rule/maintenance/civil-check/measured_value@2026-04",
  "category": "maintenance/civil-check",
  "field_key": "measured_value",
  "operator": "eq",
  "threshold_value": "4",
  "unit": "℃",
  "severity": "mandatory",
  "norm_ref": "5.5.1",
  "source_line": "4 应将再生路面碾压至要求的压实度。开放交通前路表温度应低于50℃。",
  "confidence": 0.82,
  "ingest_job_id": "ingest-e2ec54c86dad4fc5",
  "candidate_id": "cand-413c3712f5b6",
  "source_std_code": "JTG-5220-2020",
  "source_level": "industry",
  "scope": "industry",
  "hash": "sha256:85bf29a9884986e95cca7068d62133eae42a3ab0fa01b213ba8236a4e09832fe"
}