{
  "rule_id": "maintenance.civil-check.strength.70.7",
  "version": "2026-04",
  "uri": "v://normref.com/rule/maintenance/civil-check/strength@2026-04",
  "category": "maintenance/civil-check",
  "field_key": "strength",
  "operator": "eq",
  "threshold_value": "4",
  "unit": "",
  "severity": "mandatory",
  "norm_ref": "70.7",
  "source_line": "4-4 喷射混凝土抗压强度试验报告和汇总计算表",
  "confidence": 0.82,
  "ingest_job_id": "ingest-03b88bfc79ba4c68",
  "candidate_id": "cand-64afa7f7018f",
  "source_std_code": "JTG-5220-2020",
  "source_level": "industry",
  "scope": "industry",
  "hash": "sha256:5ed856c46983f30aa27e9541fbe3c83bf62da6570b66d1c0ddbdd506c1d41add"
}