{
  "rule_id": "maintenance.civil-check.measured_value.9.5.3",
  "version": "2026-04",
  "uri": "v://normref.com/rule/maintenance/civil-check/measured_value@2026-04",
  "category": "maintenance/civil-check",
  "field_key": "measured_value",
  "operator": "gte",
  "threshold_value": "2",
  "unit": "",
  "severity": "mandatory",
  "norm_ref": "9.5.3",
  "source_line": "2 沥青面层：当 K≥ K ，且全部测点压实度大于或等于规定值减 1 个百分点时，",
  "confidence": 0.82,
  "ingest_job_id": "ingest-e2ec54c86dad4fc5",
  "candidate_id": "cand-f57306dd5b08",
  "source_std_code": "JTG-5220-2020",
  "source_level": "industry",
  "scope": "industry",
  "hash": "sha256:89328db85980fd64ea12aec89e1538c046f17fbd3ad21059d472fc3cb3cd1220"
}