{
  "rule_id": "maintenance.civil-check.strength.9.5",
  "version": "2026-04",
  "uri": "v://normref.com/rule/maintenance/civil-check/strength@2026-04",
  "category": "maintenance/civil-check",
  "field_key": "strength",
  "operator": "eq",
  "threshold_value": "166",
  "unit": "",
  "severity": "mandatory",
  "norm_ref": "9.5",
  "source_line": "附录C 水泥混凝土弯拉强度评定 ......................................................................... 166",
  "confidence": 0.82,
  "ingest_job_id": "ingest-03b88bfc79ba4c68",
  "candidate_id": "cand-31a633ef69d0",
  "source_std_code": "JTG-5220-2020",
  "source_level": "industry",
  "scope": "industry",
  "hash": "sha256:78fa20c5094fa5f830e897c6b49428762b06c612c5187dbf31e5e5861427205f"
}