{
  "rule_id": "maintenance.civil-check.measured_value.0.80",
  "version": "2026-04",
  "uri": "v://normref.com/rule/maintenance/civil-check/measured_value@2026-04",
  "category": "maintenance/civil-check",
  "field_key": "measured_value",
  "operator": "gte",
  "threshold_value": "10",
  "unit": "",
  "severity": "mandatory",
  "norm_ref": "0.80",
  "source_line": "n 10～14 15～19 ≥20",
  "confidence": 0.82,
  "ingest_job_id": "ingest-e2ec54c86dad4fc5",
  "candidate_id": "cand-e9fa83487367",
  "source_std_code": "JTG-5220-2020",
  "source_level": "industry",
  "scope": "industry",
  "hash": "sha256:2ea4ffe437077a25986d3c57d70cea047527cde50bc228d8b37c79b00619f4cf"
}