{
  "rule_id": "maintenance.civil-check.measured_value.8.5.1",
  "version": "2026-04",
  "uri": "v://normref.com/rule/maintenance/civil-check/measured_value@2026-04",
  "category": "maintenance/civil-check",
  "field_key": "measured_value",
  "operator": "eq",
  "threshold_value": "5",
  "unit": "",
  "severity": "mandatory",
  "norm_ref": "8.5.1",
  "source_line": "5 路肩和中央分隔带的土基压实度不应小于设计值，达不到压实度要求的路段",
  "confidence": 0.82,
  "ingest_job_id": "ingest-e2ec54c86dad4fc5",
  "candidate_id": "cand-47c8a6f0ad72",
  "source_std_code": "JTG-5220-2020",
  "source_level": "industry",
  "scope": "industry",
  "hash": "sha256:b9a9f41dfa25379d632c64f7dd071189c291459cb62a6bf29a1e11644b9d43f7"
}