{
  "rule_id": "maintenance.civil-check.measured_value.70.7",
  "version": "2026-04",
  "uri": "v://normref.com/rule/maintenance/civil-check/measured_value@2026-04",
  "category": "maintenance/civil-check",
  "field_key": "measured_value",
  "operator": "eq",
  "threshold_value": "1",
  "unit": "",
  "severity": "mandatory",
  "norm_ref": "70.7",
  "source_line": "K.1 养护工程质量检验评定用表",
  "confidence": 0.82,
  "ingest_job_id": "ingest-e2ec54c86dad4fc5",
  "candidate_id": "cand-3617c97e33ca",
  "source_std_code": "JTG-5220-2020",
  "source_level": "industry",
  "scope": "industry",
  "hash": "sha256:70d49cc8df00ae0093d999536533387e1c230cb550c405707e41d3828f560b5d"
}