{
  "rule_id": "maintenance.civil-check.measured_value.7.8.2",
  "version": "2026-04",
  "uri": "v://normref.com/rule/maintenance/civil-check/measured_value@2026-04",
  "category": "maintenance/civil-check",
  "field_key": "measured_value",
  "operator": "tolerance",
  "threshold_value": "4",
  "unit": "mm",
  "severity": "mandatory",
  "norm_ref": "7.8.2",
  "source_line": "4 植筋间距(mm) ±10 尺量：每10m检查5处",
  "confidence": 0.82,
  "ingest_job_id": "ingest-e2ec54c86dad4fc5",
  "candidate_id": "cand-eebe7efdd891",
  "source_std_code": "JTG-5220-2020",
  "source_level": "industry",
  "scope": "industry",
  "hash": "sha256:e984ae0bc65128cc6135ee7772210066d16c9453f4f51ce3391dbe0f9ff2a588"
}