{
  "rule_id": "maintenance.civil-check.strength.9.5.2",
  "version": "2026-04",
  "uri": "v://normref.com/rule/maintenance/civil-check/strength@2026-04",
  "category": "maintenance/civil-check",
  "field_key": "strength",
  "operator": "eq",
  "threshold_value": "0.2",
  "unit": "",
  "severity": "mandatory",
  "norm_ref": "9.5.2",
  "source_line": "D.0.2 明确了水泥混凝土抗压强度的检验评定单元；根据养护工程的施工特点，",
  "confidence": 0.82,
  "ingest_job_id": "ingest-03b88bfc79ba4c68",
  "candidate_id": "cand-cd3732fd2aa2",
  "source_std_code": "JTG-5220-2020",
  "source_level": "industry",
  "scope": "industry",
  "hash": "sha256:a1c209c73c19674a5ada478f308fd4f88b22f09b75c57343fdedabb01b167290"
}