{
  "rule_id": "maintenance.civil-check.measured_value.70.7",
  "version": "2026-04",
  "uri": "v://normref.com/rule/maintenance/civil-check/measured_value@2026-04",
  "category": "maintenance/civil-check",
  "field_key": "measured_value",
  "operator": "eq",
  "threshold_value": "2",
  "unit": "m",
  "severity": "mandatory",
  "norm_ref": "70.7",
  "source_line": "置的荷载读数在2min 内无下降或下降幅度不超过5%的检验荷载时，该试样拉拔承载力",
  "confidence": 0.82,
  "ingest_job_id": "ingest-03b88bfc79ba4c68",
  "candidate_id": "cand-846386d40835",
  "source_std_code": "JTG-5220-2020",
  "source_level": "industry",
  "scope": "industry",
  "hash": "sha256:ee3414cb9ba6e665053ae6af64af957d42e502f9733dc1ab6803d5c612edbf05"
}