{
  "rule_id": "maintenance.civil-check.measured_value.9.5.2",
  "version": "2026-04",
  "uri": "v://normref.com/rule/maintenance/civil-check/measured_value@2026-04",
  "category": "maintenance/civil-check",
  "field_key": "measured_value",
  "operator": "range",
  "threshold_value": "1.1",
  "unit": "",
  "severity": "mandatory",
  "norm_ref": "9.5.2",
  "source_line": "量检验评定表指本标准附录 K.1.1～K.1.4 规定的质量检验评定表；4）监理质量控",
  "confidence": 0.82,
  "ingest_job_id": "ingest-03b88bfc79ba4c68",
  "candidate_id": "cand-ab062af5bbe4",
  "source_std_code": "JTG-5220-2020",
  "source_level": "industry",
  "scope": "industry",
  "hash": "sha256:ae81b794a537773e7e902d00a26b9f680529abe09960cd56f3fde06c62c7e21a"
}