{
  "rule_id": "maintenance.civil-check.measured_value.6.30.2",
  "version": "2026-04",
  "uri": "v://normref.com/rule/maintenance/civil-check/measured_value@2026-04",
  "category": "maintenance/civil-check",
  "field_key": "measured_value",
  "operator": "tolerance",
  "threshold_value": "2",
  "unit": "mm",
  "severity": "mandatory",
  "norm_ref": "6.30.2",
  "source_line": "2 注浆孔位偏移(mm) ±50 尺量：抽查20%",
  "confidence": 0.82,
  "ingest_job_id": "ingest-e2ec54c86dad4fc5",
  "candidate_id": "cand-af25e4022f8a",
  "source_std_code": "JTG-5220-2020",
  "source_level": "industry",
  "scope": "industry",
  "hash": "sha256:a844d86ecc3a497734fe5f6a2a6003465e36d1ddfcd319fe55a1edbefea4d042"
}