{
  "rule_id": "maintenance.civil-check.measured_value.70.7",
  "version": "2026-04",
  "uri": "v://normref.com/rule/maintenance/civil-check/measured_value@2026-04",
  "category": "maintenance/civil-check",
  "field_key": "measured_value",
  "operator": "eq",
  "threshold_value": "3",
  "unit": "mm",
  "severity": "mandatory",
  "norm_ref": "70.7",
  "source_line": "选取3块100mm×100mm 的面积，进行同条件的表面处理，作为粘贴检验用钢标准",
  "confidence": 0.82,
  "ingest_job_id": "ingest-03b88bfc79ba4c68",
  "candidate_id": "cand-be039266eb9f",
  "source_std_code": "JTG-5220-2020",
  "source_level": "industry",
  "scope": "industry",
  "hash": "sha256:c231cc5f6db9870aafbef1d03ec16cb706e03c803b82ba4794417d24c01d8f0c"
}